pylegiscan/__init__.py
pylegiscan/pylegiscan.py
pylegiscan-0.1.1.dist-info/METADATA
pylegiscan-0.1.1.dist-info/WHEEL
pylegiscan-0.1.1.dist-info/RECORD
