Metadata-Version: 2.1
Name: pylegiscan
Version: 0.1.1
Summary: 
Author: Your Name
Author-email: you@example.com
Requires-Python: >=3.11,<4.0
Classifier: Programming Language :: Python :: 3
Classifier: Programming Language :: Python :: 3.11
Classifier: Programming Language :: Python :: 3.12
Requires-Dist: pandas (>=2.2.2,<3.0.0)
Requires-Dist: pyarrow (>=17.0.0,<18.0.0)
Requires-Dist: pytest (>=8.3.2,<9.0.0)
Requires-Dist: requests (>=2.32.3,<3.0.0)
